zen_mapper/__init__.py
zen_mapper/adapters.py
zen_mapper/cover.py
zen_mapper/mapper.py
zen_mapper/py.typed
zen_mapper/types.py
zen_mapper-0.3.0.dist-info/METADATA
zen_mapper-0.3.0.dist-info/WHEEL
zen_mapper-0.3.0.dist-info/RECORD
