Metadata-Version: 2.4
Name: zen-mapper
Version: 0.3.0
Summary: Mapper without the noise
Project-URL: Homepage, https://github.com/zen-mapper/zen-mapper
Project-URL: Bug Tracker, https://github.com/zen-mapper/zen-mapper/issues
Author-email: Ethan Rooke <pypi@ethan.roo.ke>
License-Expression: ISC
Requires-Python: >=3.10
Requires-Dist: numpy>=1.26.0
Requires-Dist: typing-extensions; python_version < '3.11'
